graphizy/__init__.py
graphizy/algorithms.py
graphizy/analysis.py
graphizy/builtin_plugins.py
graphizy/cli.py
graphizy/config.py
graphizy/data_interface.py
graphizy/drawing.py
graphizy/exceptions.py
graphizy/main.py
graphizy/memory.py
graphizy/networkx_bridge.py
graphizy/plugin_examples.py
graphizy/plugins.py
graphizy/plugins_examples.py
graphizy/plugins_logic.py
graphizy/positions.py
graphizy/simulator.py
graphizy/streaming.py
graphizy/utils.py
graphizy/weight.py
graphizy-0.1.20.dist-info/licenses/LICENSE
graphizy-0.1.20.dist-info/METADATA
graphizy-0.1.20.dist-info/WHEEL
graphizy-0.1.20.dist-info/entry_points.txt
graphizy-0.1.20.dist-info/top_level.txt
graphizy-0.1.20.dist-info/RECORD
