Metadata-Version: 2.4
Name: graphizy
Version: 0.1.20
Summary: Graphizy is a fast, flexible Python library for building and analyzing computational geometry-based graphs from 2D coordinates.
Author-email: Charles Fosseprez <charles.fosseprez.pro@gmail.com>
License: GPL-2.0-or-later
Project-URL: Homepage, https://github.com/cfosseprez/graphizy
Project-URL: Repository, https://github.com/cfosseprez/graphizy
Project-URL: Documentation, https://graphizy.readthedocs.io/en/latest/
Project-URL: Issues, https://github.com/cfosseprez/graphizy/issues
Keywords: graph,delaunay,triangulation,visualization,computational-geometry
Classifier: Development Status :: 4 - Beta
Classifier: Intended Audience :: Science/Research
Classifier: License :: OSI Approved :: GNU General Public License v2 (GPLv2)
Classifier: Programming Language :: Python :: 3
Classifier: Programming Language :: Python :: 3.8
Classifier: Programming Language :: Python :: 3.9
Classifier: Programming Language :: Python :: 3.10
Classifier: Programming Language :: Python :: 3.11
Classifier: Programming Language :: Python :: 3.12
Classifier: Topic :: Scientific/Engineering :: Mathematics
Classifier: Topic :: Scientific/Engineering :: Visualization
Requires-Python: >=3.8
License-File: LICENSE
Requires-Dist: numpy>=1.20.0
Requires-Dist: opencv-python>=4.5.0
Requires-Dist: python-igraph>=0.9.0
Requires-Dist: scipy>=1.7.0
Requires-Dist: networkx>=3.0
Provides-Extra: dev
Requires-Dist: pytest>=6.0; extra == "dev"
Requires-Dist: pytest-cov>=2.0; extra == "dev"
Requires-Dist: pytest-asyncio; extra == "dev"
Requires-Dist: black>=22.0; extra == "dev"
Requires-Dist: pandas>=1.3.0; extra == "dev"
Requires-Dist: matplotlib>=3.5.0; extra == "dev"
Requires-Dist: flake8>=4.0; extra == "dev"
Requires-Dist: mypy>=0.910; extra == "dev"
Requires-Dist: psutil>=5.8.0; extra == "dev"
Requires-Dist: memory-profiler>=0.60.0; extra == "dev"
Requires-Dist: pytest-monitor>=1.6.0; extra == "dev"
Provides-Extra: docs
Requires-Dist: sphinx>=7.0.0; extra == "docs"
Requires-Dist: sphinx-rtd-theme>=2.0.0; extra == "docs"
Requires-Dist: sphinx-copybutton>=0.5.2; extra == "docs"
Requires-Dist: myst-parser>=2.0.0; extra == "docs"
Requires-Dist: matplotlib>=3.5.0; extra == "docs"
Requires-Dist: seaborn>=0.13.2; extra == "docs"
Requires-Dist: yaml; extra == "docs"
Requires-Dist: toml; extra == "docs"
Dynamic: license-file
